pycounts_pjlearn/__init__.py
pycounts_pjlearn/plotting.py
pycounts_pjlearn/pycounts_pjlearn.py
pycounts_pjlearn-0.1.0.dist-info/LICENSE
pycounts_pjlearn-0.1.0.dist-info/METADATA
pycounts_pjlearn-0.1.0.dist-info/WHEEL
pycounts_pjlearn-0.1.0.dist-info/RECORD
