Metadata-Version: 2.1
Name: pycounts_pjlearn
Version: 0.1.0
Summary: Calculate word counts in a text file! A learning project of the book Python packages
License: MIT
Author: Pan Ji
Requires-Python: >=3.9
Classifier: License :: OSI Approved :: MIT License
Classifier: Programming Language :: Python :: 3
Classifier: Programming Language :: Python :: 3.9
Classifier: Programming Language :: Python :: 3.10
Classifier: Programming Language :: Python :: 3.11
Classifier: Programming Language :: Python :: 3.12
Requires-Dist: matplotlib (>=3.4.3)
